rssarchive/__init__.py
rssarchive-0.5.2.data/scripts/rssarchive
rssarchive-0.5.2.dist-info/LICENSE
rssarchive-0.5.2.dist-info/METADATA
rssarchive-0.5.2.dist-info/WHEEL
rssarchive-0.5.2.dist-info/top_level.txt
rssarchive-0.5.2.dist-info/RECORD
