Metadata-Version: 2.1
Name: rssarchive
Version: 0.5.2
Summary: Archive your RSS into SQLite:
Home-page: http://github.com/suatatan/rssarchive
Author: Suat ATAN
Author-email: suatatan@gmail.com
License: MIT
Keywords: RSS,SQlite,News
Platform: UNKNOWN
Requires-Dist: newspaper3k
Requires-Dist: feedparser
